chatbot/__init__.py
chatbot/module.py
chatbot_gpt2-0.1.0.dist-info/LICENSE
chatbot_gpt2-0.1.0.dist-info/METADATA
chatbot_gpt2-0.1.0.dist-info/WHEEL
chatbot_gpt2-0.1.0.dist-info/top_level.txt
chatbot_gpt2-0.1.0.dist-info/RECORD
