Metadata-Version: 2.1
Name: chatbot-gpt2
Version: 0.1.0
Summary: Chatbot package
Home-page: https://github.com/yourusername/my_package
Author: Rahul Kumar Bharti
Author-email: rahul_kbharti2002@gmail.com
Classifier: Programming Language :: Python :: 3
Classifier: License :: OSI Approved :: MIT License
Classifier: Operating System :: OS Independent
Requires-Python: >=3.6
License-File: LICENSE
